ResearchTools/Caching.py
ResearchTools/Dict.py
ResearchTools/Events.py
ResearchTools/Filesystem.py
ResearchTools/Geometry.py
ResearchTools/Integration.py
ResearchTools/Iterable.py
ResearchTools/Multiprocessing.py
ResearchTools/Sweep.py
ResearchTools/Util.py
ResearchTools/__init__.py
researchtools-0.0.4.dist-info/LICENSE
researchtools-0.0.4.dist-info/WHEEL
researchtools-0.0.4.dist-info/METADATA
researchtools-0.0.4.dist-info/RECORD
