Metadata-Version: 2.1
Name: ResearchTools
Version: 0.0.4
Summary: A package for generic tools that may be useful in scientific research projects. Python 3.10+
Author-email: Laurent MacKay <laurent.mackay@gmail.com>
Classifier: License :: OSI Approved :: GNU General Public License v3 or later (GPLv3+)
